{
  "//": "made by namar0x0309 with ❤️ at GoAIX",
  "mcpServers": {
    "wekan-username": {
      "command": "node",
      "args": ["dist/server.js"],
      "env": {
        "WEKAN_BASE_URL": "https://wekan.uan.com.br",
        "WEKAN_USERNAME": "username",
        "WEKAN_PASSWORD": "password!"
      },
      "transport": "stdio"
    },
    "wekan": {
      "command": "node",
      "args": ["dist/server.js"],
      "env": {
        "WEKAN_BASE_URL": "https://wekan.uan.com.br",
        "WEKAN_API_TOKEN": "88maf3PteMjb9vSpI2WGjhcOwr461rlqwSiuRNS1rw1",
        "WEKAN_USER_ID": "XvR5MTWzozNxQwnJB"
      },
      "transport": "stdio"
    }
  }
}
